setup.py
src/tenpy/__init__.py
src/tenpy/builder.py
src/tenpy/cache.py
src/tenpy/config.py
src/tenpy/etree.py
src/tenpy/helper.py
src/tenpy/parser.py
src/tenpy.egg-info/PKG-INFO
src/tenpy.egg-info/SOURCES.txt
src/tenpy.egg-info/dependency_links.txt
src/tenpy.egg-info/requires.txt
src/tenpy.egg-info/top_level.txt
src/tenpy/test/__init__.py
src/tenpy/test/test_builder.py
src/tenpy/test/test_cache.py
src/tenpy/test/test_etree.py
src/tenpy/test/test_helper.py
src/tenpy/test/test_parser.py
src/tenpy/test/test_tenpy_config.py