Metadata-Version: 1.0
Name: tenpy
Version: 0.1
Summary: Template engine which realized the concept of 'Independence of Presentation Logic' for Python 3
Home-page: https://bitbucket.org/naoina/tenpy
Author: Naoya Inada
Author-email: naoina@naniyueni.org
License: BSD
Platform: UNKNOWN
Classifier: Development Status :: 3 - Alpha
Classifier: Environment :: Web Environment
Classifier: Intended Audience :: Developers
Classifier: License :: OSI Approved :: BSD License
Classifier: Operating System :: OS Independent
Classifier: Programming Language :: Python :: 3
Classifier: Topic :: Internet :: WWW/HTTP :: Dynamic Content
